MANIFEST.in
README.md
setup.cfg
setup.py
restifier/__init__.py
restifier/decorators.py
restifier/messages.py
restifier/middleware.py
restifier/mimeparse.py
restifier/validators.py
restifier/variabledecode.py
restifier/xmltodict.py
restifier.egg-info/PKG-INFO
restifier.egg-info/SOURCES.txt
restifier.egg-info/dependency_links.txt
restifier.egg-info/requires.txt
restifier.egg-info/top_level.txt