Metadata-Version: 1.1
Name: restifier
Version: 1.0.4
Summary: A data validation and REST auto-documenter for APIs.
Home-page: https://github.com/mentat/restifier
Author: Jesse Lovelace
Author-email: jesse.lovelace@gmail.com
License: MIT
Keywords: rest api swagger development
Platform: UNKNOWN
Classifier: Development Status :: 5 - Production/Stable
Classifier: Intended Audience :: Developers
Classifier: License :: OSI Approved :: MIT License
Classifier: Programming Language :: Python :: 2
Classifier: Programming Language :: Python :: 2.6
Classifier: Programming Language :: Python :: 2.7
Classifier: Programming Language :: Python :: 3
Classifier: Programming Language :: Python :: 3.2
Classifier: Programming Language :: Python :: 3.3
Classifier: Programming Language :: Python :: 3.4
Classifier: Programming Language :: Python :: 3.5
